dateutils/__init__.py
dateutils/types.py
dateutils/utils.py
p1_dateutils-0.1.7.dist-info/METADATA
p1_dateutils-0.1.7.dist-info/WHEEL
p1_dateutils-0.1.7.dist-info/top_level.txt
p1_dateutils-0.1.7.dist-info/RECORD
