Metadata-Version: 2.1
Name: p1-dateutils
Version: 0.1.7
Summary: Timezone Wrapper for Dekoruma Internal Use
Home-page: 
Author: Engineering
Author-email: engineering@dekoruma.com
License: MIT
